nctevnhn/__init__.py
nctevnhn/app.py
nctevnhn-2021.10.1.dist-info/LICENSE
nctevnhn-2021.10.1.dist-info/METADATA
nctevnhn-2021.10.1.dist-info/WHEEL
nctevnhn-2021.10.1.dist-info/top_level.txt
nctevnhn-2021.10.1.dist-info/RECORD
