Metadata-Version: 2.1
Name: nctevnhn
Version: 2021.10.1
Summary: https://vnhass.blogspot.com/
Home-page: https://github.com/pypa/sampleproject
Author: @trumxuquang
Author-email: trumxuquang@gmail.com
License: UNKNOWN
Platform: UNKNOWN
Classifier: Programming Language :: Python :: 3
Classifier: Programming Language :: Python :: 3.6
Classifier: Programming Language :: Python :: 3.7
Classifier: Programming Language :: Python :: 3.8
Classifier: Programming Language :: Python :: 3.9
Classifier: Programming Language :: Python :: 3 :: Only
License-File: LICENSE
Requires-Dist: pybase64 (<5,>=1.2.0)
Requires-Dist: requests (<3,>=2.25)
Requires-Dist: pyparsing (<3,>=2.4)
Requires-Dist: jsons (<3,>=1.5.1)
